{"response":{"count":11,"items":[{"id":250,"from_id":437571510,"owner_id":295572920,"date":1558266567,"post_type":"post","text":"Вам отправили подарок. Узнай какой подарок в Android приложении - https:\/\/vk.cc\/9iMann","attachments":[{"type":"photo","photo":{"id":456239019,"album_id":-7,"owner_id":-168397160,"user_id":100,"sizes":[{"type":"m","url":"https:\/\/sun1.43222.userapi.com\/c834100\/v834100333\/181bae\/3vM1DI4DHBI.jpg","width":130,"height":130},{"type":"o","url":"https:\/\/sun2.43222.userapi.com\/c834100\/v834100333\/181bb0\/fWe6f5foqq0.jpg","width":130,"height":130},{"type":"p","url":"https:\/\/sun2.43222.userapi.com\/c834100\/v834100333\/181bb1\/1F5pBHgOQSI.jpg","width":200,"height":200},{"type":"q","url":"https:\/\/sun2.43222.userapi.com\/c834100\/v834100333\/181bb2\/uD4ONMn9qUw.jpg","width":320,"height":320},{"type":"r","url":"https:\/\/sun2.43222.userapi.com\/c834100\/v834100333\/181bb3\/3n2W-bgkyPg.jpg","width":510,"height":510},{"type":"s","url":"https:\/\/sun1.43222.userapi.com\/c834100\/v834100333\/181bad\/tjJhDKDIbJc.jpg","width":75,"height":75},{"type":"x","url":"https:\/\/sun1.43222.userapi.com\/c834100\/v834100333\/181baf\/7a2P209PLCw.jpg","width":600,"height":600}],"text":"","date":1530529496,"post_id":2,"access_key":"85dd83bace64ba147e"}}],"post_source":{"type":"api"},"comments":{"count":0,"can_post":1,"groups_can_post":true},"likes":{"count":0,"user_likes":0,"can_like":1,"can_publish":0},"reposts":{"count":0,"user_reposted":0},"is_favorite":false},{"id":248,"from_id":295572920,"owner_id":295572920,"date":1544887819,"post_type":"post","text":"","attachments":[{"type":"photo","photo":{"id":456239148,"album_id":-6,"owner_id":295572920,"sizes":[{"type":"m","url":"https:\/\/pp.userapi.com\/c845124\/v845124826\/157541\/AFdlwnDOLls.jpg","width":97,"height":130},{"type":"o","url":"https:\/\/pp.userapi.com\/c845124\/v845124826\/157544\/WOJAHkmDow8.jpg","width":130,"height":173},{"type":"p","url":"https:\/\/pp.userapi.com\/c845124\/v845124826\/157545\/3PoQhaeEt5s.jpg","width":200,"height":267},{"type":"q","url":"https:\/\/pp.userapi.com\/c845124\/v845124826\/157546\/atnlKBixOAw.jpg","width":320,"height":427},{"type":"r","url":"https:\/\/pp.userapi.com\/c845124\/v845124826\/157547\/xoe8k_8aOC8.jpg","width":480,"height":640},{"type":"s","url":"https:\/\/pp.userapi.com\/c845124\/v845124826\/157540\/Pec2E4UQWBQ.jpg","width":56,"height":75},{"type":"x","url":"https:\/\/pp.userapi.com\/c845124\/v845124826\/157542\/Qcu1SPA0pQU.jpg","width":453,"height":604},{"type":"y","url":"https:\/\/pp.userapi.com\/c845124\/v845124826\/157543\/VqWx84YyrSM.jpg","width":480,"height":640}],"text":"","date":1544887819,"post_id":248}}],"post_source":{"type":"api","platform":"iphone","data":"profile_photo"},"comments":{"count":0,"can_post":1,"groups_can_post":true},"likes":{"count":25,"user_likes":0,"can_like":1,"can_publish":1},"reposts":{"count":0,"user_reposted":0},"views":{"count":228},"is_favorite":false},{"id":247,"from_id":473765630,"owner_id":295572920,"date":1540905870,"post_type":"post","text":"Про тебя набралось много ответов от друзей. \n Ты даже не представляешь какой самый популярный ответ про тебя  \n Полная информаця по ссылке : https:\/\/vk.cc\/81gAwU","attachments":[{"type":"page","page":{"id":55402984,"group_id":90205912,"title":"Я думаю что ты ...","who_can_view":2,"who_can_edit":0,"edited":0,"created":1530817153,"views":1203514,"view_url":"https:\/\/m.vk.com\/page-90205912_55402984?api_view=e0e02a2aed5b50ef5147414c7237b0"}},{"type":"link","link":{"url":"https:\/\/vk.cc\/81gAwU","title":"ИнфоЦентр - Ответы о тебе | ВКонтакте","description":"ИнфоЦентр - приложение, в котором можно узнать всю полезную информацию про свою страничку ВКонтакте : - Сканирование авы - Признания друзей - Чувства друзей - Оценки друзей -- И много чего другого.","target":"internal","photo":{"id":456239262,"album_id":-2,"owner_id":100,"sizes":[{"type":"k","url":"https:\/\/pp.userapi.com\/c846122\/v846122307\/11881d\/M3xnMKjmabY.jpg","width":991,"height":480},{"type":"l","url":"https:\/\/pp.userapi.com\/c846122\/v846122307\/11881c\/ojZI1QMslmQ.jpg","width":537,"height":240},{"type":"m","url":"https:\/\/pp.userapi.com\/c846122\/v846122307\/118819\/fFI6PS9maxo.jpg","width":130,"height":79},{"type":"p","url":"https:\/\/pp.userapi.com\/c846122\/v846122307\/11881b\/y-ZQ2yLWu3Q.jpg","width":260,"height":157},{"type":"s","url":"https:\/\/pp.userapi.com\/c846122\/v846122307\/118818\/3a0_Y9ploCY.jpg","width":75,"height":45},{"type":"x","url":"https:\/\/pp.userapi.com\/c846122\/v846122307\/11881a\/KoZKqrgoGaQ.jpg","width":150,"height":91}],"text":"","date":1540905874},"is_favorite":false}}],"post_source":{"type":"api"},"comments":{"count":0,"can_post":1,"groups_can_post":true},"likes":{"count":0,"user_likes":0,"can_like":1,"can_publish":0},"reposts":{"count":0,"user_reposted":0},"is_favorite":false},{"id":246,"from_id":341818686,"owner_id":295572920,"date":1540015850,"post_type":"post","text":"Про тебя набралось много ответов от друзей. \n Ты даже не представляешь какой самый популярный ответ про тебя  \n Полная информаця по ссылке : https:\/\/vk.cc\/81gAwU","attachments":[{"type":"page","page":{"id":55402984,"group_id":90205912,"title":"Я думаю что ты ...","who_can_view":2,"who_can_edit":0,"edited":0,"created":1530817153,"views":1203514,"view_url":"https:\/\/m.vk.com\/page-90205912_55402984?api_view=e0e02a2aed5b50ef5147414c7237b0"}},{"type":"link","link":{"url":"https:\/\/vk.cc\/81gAwU","title":"ИнфоЦентр - Ответы о тебе | ВКонтакте","description":"ИнфоЦентр - приложение, в котором можно узнать всю полезную информацию про свою страничку ВКонтакте : - Сканирование авы - Признания друзей - Чувства друзей - Оценки друзей -- И много чего другого.","target":"internal","photo":{"id":456246973,"album_id":-2,"owner_id":100,"sizes":[{"type":"k","url":"https:\/\/pp.userapi.com\/c849336\/v849336337\/9e2aa\/5qynkz2DTs8.jpg","width":991,"height":480},{"type":"l","url":"https:\/\/pp.userapi.com\/c849336\/v849336337\/9e2a9\/dp_VpBxarRM.jpg","width":537,"height":240},{"type":"m","url":"https:\/\/pp.userapi.com\/c849336\/v849336337\/9e2a6\/9wNCP_0UGNY.jpg","width":130,"height":79},{"type":"p","url":"https:\/\/pp.userapi.com\/c849336\/v849336337\/9e2a8\/1wFiQXvcqqQ.jpg","width":260,"height":157},{"type":"s","url":"https:\/\/pp.userapi.com\/c849336\/v849336337\/9e2a5\/gjWdqIrSqjA.jpg","width":75,"height":45},{"type":"x","url":"https:\/\/pp.userapi.com\/c849336\/v849336337\/9e2a7\/9uSGHHdaluE.jpg","width":150,"height":91}],"text":"","date":1540015857},"is_favorite":false}}],"post_source":{"type":"api"},"comments":{"count":0,"can_post":1,"groups_can_post":true},"likes":{"count":0,"user_likes":0,"can_like":1,"can_publish":0},"reposts":{"count":0,"user_reposted":0},"is_favorite":false},{"id":245,"from_id":341818686,"owner_id":295572920,"date":1539508260,"post_type":"post","text":"Про тебя набралось много ответов от друзей. \n Ты даже не представляешь какой самый популярный ответ про тебя  \n Полная информаця по ссылке : https:\/\/vk.cc\/81gAwU","attachments":[{"type":"page","page":{"id":55402984,"group_id":90205912,"title":"Я думаю что ты ...","who_can_view":2,"who_can_edit":0,"edited":0,"created":1530817153,"views":1203514,"view_url":"https:\/\/m.vk.com\/page-90205912_55402984?api_view=e0e02a2aed5b50ef5147414c7237b0"}},{"type":"link","link":{"url":"https:\/\/vk.cc\/81gAwU","title":"ИнфоЦентр - Ответы о тебе | ВКонтакте","description":"ИнфоЦентр - приложение, в котором можно узнать всю полезную информацию про свою страничку ВКонтакте : - Сканирование авы - Признания друзей - Чувства друзей - Оценки друзей -- И много чего другого.","target":"internal","photo":{"id":456246838,"album_id":-2,"owner_id":100,"sizes":[{"type":"k","url":"https:\/\/pp.userapi.com\/c846322\/v846322086\/10ae3c\/lV_3XRFhrMk.jpg","width":991,"height":480},{"type":"l","url":"https:\/\/pp.userapi.com\/c846322\/v846322086\/10ae3b\/aodLa3LQglI.jpg","width":537,"height":240},{"type":"m","url":"https:\/\/pp.userapi.com\/c846322\/v846322086\/10ae38\/MCYPnxzOsVs.jpg","width":130,"height":79},{"type":"p","url":"https:\/\/pp.userapi.com\/c846322\/v846322086\/10ae3a\/6q1LjFDLqnc.jpg","width":260,"height":157},{"type":"s","url":"https:\/\/pp.userapi.com\/c846322\/v846322086\/10ae37\/S4Y5-cGacL0.jpg","width":75,"height":45},{"type":"x","url":"https:\/\/pp.userapi.com\/c846322\/v846322086\/10ae39\/Fz_A0gZtx9A.jpg","width":150,"height":91}],"text":"","date":1539508262},"is_favorite":false}}],"post_source":{"type":"api"},"comments":{"count":0,"can_post":1,"groups_can_post":true},"likes":{"count":0,"user_likes":0,"can_like":1,"can_publish":0},"reposts":{"count":0,"user_reposted":0},"is_favorite":false},{"id":244,"from_id":426651961,"owner_id":295572920,"date":1533118666,"post_type":"post","text":"Про тебя набралось много ответов от друзей. \n Ты даже не представляешь какой самый популярный ответ про тебя  \n Полная информаця по ссылке : https:\/\/vk.cc\/81gAwU","attachments":[{"type":"page","page":{"id":55402984,"group_id":90205912,"title":"Я думаю что ты ...","who_can_view":2,"who_can_edit":0,"edited":0,"created":1530817153,"views":1203514,"view_url":"https:\/\/m.vk.com\/page-90205912_55402984?api_view=e0e02a2aed5b50ef5147414c7237b0"}},{"type":"link","link":{"url":"https:\/\/vk.cc\/81gAwU","title":"ИнфоЦентр - Ответы о тебе | ВКонтакте","description":"ИнфоЦентр - приложение, в котором можно узнать всю полезную информацию про свою страничку ВКонтакте : - Сканирование авы - Признания друзей - Чувства друзей - Оценки друзей -- И много чего другого.","target":"internal","photo":{"id":456239188,"album_id":-2,"owner_id":100,"sizes":[{"type":"k","url":"https:\/\/pp.userapi.com\/c824501\/v824501889\/19a4a4\/cuzcHi_wQM8.jpg","width":991,"height":480},{"type":"l","url":"https:\/\/pp.userapi.com\/c824501\/v824501889\/19a4a3\/sc66tENdRQ8.jpg","width":537,"height":240},{"type":"m","url":"https:\/\/pp.userapi.com\/c824501\/v824501889\/19a4a0\/s6tiblRpQas.jpg","width":130,"height":79},{"type":"p","url":"https:\/\/pp.userapi.com\/c824501\/v824501889\/19a4a2\/uXmeXfPJVsc.jpg","width":260,"height":157},{"type":"s","url":"https:\/\/pp.userapi.com\/c824501\/v824501889\/19a49f\/4Qae3HFqM5o.jpg","width":75,"height":45},{"type":"x","url":"https:\/\/pp.userapi.com\/c824501\/v824501889\/19a4a1\/0CxBUfTFioU.jpg","width":150,"height":91}],"text":"","date":1533118669},"is_favorite":false}}],"post_source":{"type":"api"},"comments":{"count":0,"can_post":1,"groups_can_post":true},"likes":{"count":0,"user_likes":0,"can_like":1,"can_publish":0},"reposts":{"count":0,"user_reposted":0},"is_favorite":false},{"id":243,"from_id":295572920,"owner_id":295572920,"date":1529513247,"post_type":"post","text":"","attachments":[{"type":"photo","photo":{"id":456239027,"album_id":-7,"owner_id":295572920,"sizes":[{"type":"m","url":"https:\/\/pp.userapi.com\/c848736\/v848736864\/d83a\/_Ds5gQe8rIQ.jpg","width":97,"height":130},{"type":"o","url":"https:\/\/pp.userapi.com\/c848736\/v848736864\/d83e\/EsdUvkoCb50.jpg","width":130,"height":173},{"type":"p","url":"https:\/\/pp.userapi.com\/c848736\/v848736864\/d83f\/T9_puG771xI.jpg","width":200,"height":267},{"type":"q","url":"https:\/\/pp.userapi.com\/c848736\/v848736864\/d840\/e4BWHj16FP4.jpg","width":320,"height":427},{"type":"r","url":"https:\/\/pp.userapi.com\/c848736\/v848736864\/d841\/ERuYZsPlTOA.jpg","width":510,"height":680},{"type":"s","url":"https:\/\/pp.userapi.com\/c848736\/v848736864\/d839\/g37nwpeu2Hg.jpg","width":56,"height":75},{"type":"x","url":"https:\/\/pp.userapi.com\/c848736\/v848736864\/d83b\/vQRILjgiGns.jpg","width":453,"height":604},{"type":"y","url":"https:\/\/pp.userapi.com\/c848736\/v848736864\/d83c\/F4GQfhSkf7Q.jpg","width":605,"height":807},{"type":"z","url":"https:\/\/pp.userapi.com\/c848736\/v848736864\/d83d\/rWBPM-7wYAY.jpg","width":720,"height":960}],"text":"","date":1529513239,"lat":44.554134,"long":34.311269,"post_id":243,"access_key":"86d45692a504bd640a"}}],"post_source":{"type":"api","platform":"iphone"},"comments":{"count":0,"can_post":1,"groups_can_post":true},"likes":{"count":3,"user_likes":0,"can_like":1,"can_publish":1},"reposts":{"count":0,"user_reposted":0},"views":{"count":131},"is_favorite":false},{"id":242,"from_id":295572920,"owner_id":295572920,"date":1529506873,"post_type":"post","text":"","attachments":[{"type":"photo","photo":{"id":456239025,"album_id":-7,"owner_id":295572920,"sizes":[{"type":"m","url":"https:\/\/pp.userapi.com\/c848732\/v848732561\/ebee\/IOoM-tfE67k.jpg","width":97,"height":130},{"type":"o","url":"https:\/\/pp.userapi.com\/c848732\/v848732561\/ebf2\/Yly_TWbviwc.jpg","width":130,"height":173},{"type":"p","url":"https:\/\/pp.userapi.com\/c848732\/v848732561\/ebf3\/VxaEpzgk2Pc.jpg","width":200,"height":267},{"type":"q","url":"https:\/\/pp.userapi.com\/c848732\/v848732561\/ebf4\/8LnxxXz50Nk.jpg","width":320,"height":427},{"type":"r","url":"https:\/\/pp.userapi.com\/c848732\/v848732561\/ebf5\/dn7c3GhyK-Q.jpg","width":510,"height":680},{"type":"s","url":"https:\/\/pp.userapi.com\/c848732\/v848732561\/ebed\/KhoDhYO7Cjk.jpg","width":56,"height":75},{"type":"x","url":"https:\/\/pp.userapi.com\/c848732\/v848732561\/ebef\/QH8QSR5NqbE.jpg","width":453,"height":604},{"type":"y","url":"https:\/\/pp.userapi.com\/c848732\/v848732561\/ebf0\/Jbwd5Wu5w5E.jpg","width":605,"height":807},{"type":"z","url":"https:\/\/pp.userapi.com\/c848732\/v848732561\/ebf1\/8hQdWTALALo.jpg","width":720,"height":960}],"text":"","date":1529506872,"lat":44.980881,"long":34.099298,"post_id":242,"access_key":"6a9fd3726b2662c108"}}],"post_source":{"type":"api","platform":"iphone"},"comments":{"count":0,"can_post":1,"groups_can_post":true},"likes":{"count":7,"user_likes":0,"can_like":1,"can_publish":1},"reposts":{"count":0,"user_reposted":0},"views":{"count":147},"is_favorite":false},{"id":212,"from_id":295572920,"owner_id":295572920,"date":1446271576,"post_type":"post","text":"","attachments":[{"type":"photo","photo":{"id":384720869,"album_id":-6,"owner_id":295572920,"sizes":[{"type":"m","url":"https:\/\/pp.userapi.com\/c623418\/v623418920\/4f534\/xWWWVcVnnEo.jpg","width":130,"height":130},{"type":"o","url":"https:\/\/pp.userapi.com\/c623418\/v623418920\/4f539\/A60cWXbGmsk.jpg","width":130,"height":130},{"type":"p","url":"https:\/\/pp.userapi.com\/c623418\/v623418920\/4f53a\/PLnEuFlfChg.jpg","width":200,"height":200},{"type":"q","url":"https:\/\/pp.userapi.com\/c623418\/v623418920\/4f53b\/MvJGuIOU_uY.jpg","width":320,"height":320},{"type":"r","url":"https:\/\/pp.userapi.com\/c623418\/v623418920\/4f53c\/7qSKJqgXlf8.jpg","width":510,"height":510},{"type":"s","url":"https:\/\/pp.userapi.com\/c623418\/v623418920\/4f533\/JN6b_7cGL-k.jpg","width":75,"height":75},{"type":"w","url":"https:\/\/pp.userapi.com\/c623418\/v623418920\/4f538\/_0vl4-Ll_24.jpg","width":1392,"height":1392},{"type":"x","url":"https:\/\/pp.userapi.com\/c623418\/v623418920\/4f535\/JYCnnLNgOoE.jpg","width":604,"height":604},{"type":"y","url":"https:\/\/pp.userapi.com\/c623418\/v623418920\/4f536\/XVjoXXNFU0Q.jpg","width":807,"height":807},{"type":"z","url":"https:\/\/pp.userapi.com\/c623418\/v623418920\/4f537\/j2RQ0DAFHiU.jpg","width":1080,"height":1080}],"text":"","date":1446271578,"post_id":212}}],"post_source":{"type":"api","platform":"android","data":"profile_photo"},"comments":{"count":0,"can_post":1,"groups_can_post":true},"likes":{"count":12,"user_likes":0,"can_like":1,"can_publish":1},"reposts":{"count":0,"user_reposted":0},"is_favorite":false},{"id":3,"from_id":295572920,"owner_id":295572920,"date":1426163644,"post_type":"post","text":"","attachments":[{"type":"photo","photo":{"id":356021272,"album_id":-7,"owner_id":295572920,"sizes":[{"type":"m","url":"https:\/\/pp.userapi.com\/c621627\/v621627920\/16c15\/7SA6LnNi2yQ.jpg","width":130,"height":87},{"type":"o","url":"https:\/\/pp.userapi.com\/c621627\/v621627920\/16c19\/PN__acuOR7o.jpg","width":130,"height":87},{"type":"p","url":"https:\/\/pp.userapi.com\/c621627\/v621627920\/16c1a\/qpa3qD8DRSo.jpg","width":200,"height":133},{"type":"q","url":"https:\/\/pp.userapi.com\/c621627\/v621627920\/16c1b\/5-qZwKgVJQI.jpg","width":320,"height":213},{"type":"r","url":"https:\/\/pp.userapi.com\/c621627\/v621627920\/16c1c\/DK2-MCJNQg4.jpg","width":510,"height":340},{"type":"s","url":"https:\/\/pp.userapi.com\/c621627\/v621627920\/16c14\/mFUSt9hgzL8.jpg","width":75,"height":50},{"type":"x","url":"https:\/\/pp.userapi.com\/c621627\/v621627920\/16c16\/6PbDDmaeJ1E.jpg","width":604,"height":403},{"type":"y","url":"https:\/\/pp.userapi.com\/c621627\/v621627920\/16c17\/4oSBg08NUqs.jpg","width":807,"height":538},{"type":"z","url":"https:\/\/pp.userapi.com\/c621627\/v621627920\/16c18\/TuYQXSWfyNc.jpg","width":1280,"height":853}],"text":"","date":1426163644,"access_key":"6686751b2aaa34dadf"}},{"type":"photos_list","photos_list":["295572920_356021272"]}],"post_source":{"type":"vk"},"comments":{"count":1,"can_post":1,"groups_can_post":true},"likes":{"count":4,"user_likes":0,"can_like":1,"can_publish":1},"reposts":{"count":0,"user_reposted":0},"is_favorite":false},{"id":1,"from_id":295572920,"owner_id":295572920,"date":1425710415,"post_type":"post","text":"","attachments":[{"type":"photo","photo":{"id":355410330,"album_id":-6,"owner_id":295572920,"sizes":[{"type":"m","url":"https:\/\/pp.userapi.com\/lyMA_hDQ1r430iaX-e1w9UZF91QXpSD2RDxJ-w\/QKrFLCMZvrA.jpg","width":130,"height":87},{"type":"o","url":"https:\/\/pp.userapi.com\/lyMA_hDQ1r430iaX-e1w9UZF91QXpSD2RDxJ-w\/QKrFLCMZvrA.jpg","width":130,"height":87},{"type":"p","url":"https:\/\/pp.userapi.com\/MkseOfRalTc5ZryFS88WgvddLTMIfeeNJ-qsCw\/8n5Q91qbXGg.jpg","width":200,"height":133},{"type":"q","url":"https:\/\/pp.userapi.com\/mTw_U_jhDM5168Hd1Jjayw1meFgqeYwJpJFm_Q\/n6SlGYZhLjA.jpg","width":320,"height":213},{"type":"r","url":"https:\/\/pp.userapi.com\/r7y2xTsnDjhcKYnIBPx2HBBujnb6D4DTakpCog\/l7W8jNapk-U.jpg","width":510,"height":340},{"type":"s","url":"https:\/\/pp.userapi.com\/YPXbxqGt1v3qFeZh1Ublb8aPmjR7b-cG1UfcDg\/5AZbv4v5xcU.jpg","width":75,"height":50},{"type":"w","url":"https:\/\/pp.userapi.com\/glihJwDmZDH1PaEKm1vzpG7OInTcZk8QBBRYxA\/ru2AGfobgiY.jpg","width":2560,"height":1707},{"type":"x","url":"https:\/\/pp.userapi.com\/KW968yx3iCieJOkLtEZ6xOl2yqbWErbIfySwNQ\/sDFJIQP0HNY.jpg","width":604,"height":403},{"type":"y","url":"https:\/\/pp.userapi.com\/SomkJk93ndYcoBplzZJ2DZ6Gi-5_RAfcs6Wi3A\/RGvP1MvfMJk.jpg","width":807,"height":538},{"type":"z","url":"https:\/\/pp.userapi.com\/mfUQoQ5fH-IHuE73YlWRT0z1BRoCJuxQQGs0Ag\/vhMBShhRFRQ.jpg","width":1280,"height":853}],"text":"","date":1425710416,"post_id":1}}],"post_source":{"type":"vk","data":"profile_photo"},"comments":{"count":0,"can_post":1,"groups_can_post":true},"likes":{"count":8,"user_likes":0,"can_like":1,"can_publish":1},"reposts":{"count":0,"user_reposted":0},"is_favorite":false}],"profiles":[{"id":295572920,"first_name":"Никита","last_name":"Червов","is_closed":false,"can_access_closed":true,"sex":2,"screen_name":"id295572920","photo_50":"https:\/\/pp.userapi.com\/c845124\/v845124826\/15754d\/xT1l5JFJY3g.jpg?ava=1","photo_100":"https:\/\/pp.userapi.com\/c845124\/v845124826\/15754c\/me49yZiqwQ4.jpg?ava=1","online":0},{"id":341818686,"first_name":"Лера","last_name":"Полуянова","is_closed":false,"can_access_closed":true,"sex":1,"screen_name":"id341818686","photo_50":"https:\/\/pp.userapi.com\/c845417\/v845417001\/8f5da\/9hnDajBYp78.jpg?ava=1","photo_100":"https:\/\/pp.userapi.com\/c845417\/v845417001\/8f5d9\/FamXt6Fp4IU.jpg?ava=1","online":1,"online_app":"2274003","online_mobile":1},{"id":426651961,"first_name":"Рома","last_name":"Кубрак","is_closed":true,"can_access_closed":false,"sex":2,"screen_name":"rkubrak","photo_50":"https:\/\/pp.userapi.com\/c849320\/v849320574\/163e0e\/uNiNp05dM2U.jpg?ava=1","photo_100":"https:\/\/pp.userapi.com\/c849320\/v849320574\/163e0d\/JOnnBGOHDsw.jpg?ava=1","online":0},{"id":437571510,"first_name":"Антон","last_name":"Петров","is_closed":false,"can_access_closed":true,"sex":2,"screen_name":"id437571510","photo_50":"https:\/\/pp.userapi.com\/c846322\/v846322034\/1f301b\/iJkRK1f35EI.jpg?ava=1","photo_100":"https:\/\/pp.userapi.com\/c846322\/v846322034\/1f301a\/C_J7yzxxnbQ.jpg?ava=1","online":1,"online_app":"2274003","online_mobile":1},{"id":473765630,"first_name":"Павел","last_name":"Сергеев","is_closed":false,"can_access_closed":true,"sex":2,"screen_name":"serfonix","photo_50":"https:\/\/pp.userapi.com\/c855632\/v855632909\/1b37a\/efPQnyhLlOw.jpg?ava=1","photo_100":"https:\/\/pp.userapi.com\/c855632\/v855632909\/1b379\/d2MYXr0I5zw.jpg?ava=1","online":0}],"groups":[{"id":90205912,"name":"ИнфоЦентр - Официальное сообщество","screen_name":"club90205912","is_closed":0,"type":"group","photo_50":"https:\/\/sun1.43222.userapi.com\/c846016\/v846016855\/20d590\/RzGF4dyffRg.jpg?ava=1","photo_100":"https:\/\/sun2.43222.userapi.com\/c846016\/v846016855\/20d58f\/EyECEUfXDVA.jpg?ava=1","photo_200":"https:\/\/sun2.43222.userapi.com\/c846016\/v846016855\/20d58e\/m_Ys9msVfxI.jpg?ava=1"}]}}